LICENSE
MANIFEST.in
README.rst
api_example.py
setup.cfg
setup.py
bin/lirconian
lirconian/__init__.py
lirconian/reply_parser.py
lirconian.egg-info/PKG-INFO
lirconian.egg-info/SOURCES.txt
lirconian.egg-info/dependency_links.txt
lirconian.egg-info/entry_points.txt
lirconian.egg-info/top_level.txt