Metadata-Version: 1.1
Name: lirconian
Version: 0.2.1
Summary: Pure Python implementation of the Lirc irsend program.
Home-page: https://github.com/bengtmartensson/Lirconian
Author: Bengt Martensson
Author-email: barf@bengt-martensson.de
License: GPLv2+
Keywords: lirc irsend API
Platform: UNKNOWN
Classifier: Programming Language :: Python :: 2.7
Classifier: Programming Language :: Python :: 3
Classifier: Development Status :: 4 - Beta
Classifier: License :: OSI Approved :: GNU General Public License v2 or later (GPLv2+)
Classifier: Environment :: Console
Classifier: Intended Audience :: Developers
Classifier: Natural Language :: English
Classifier: Topic :: Software Development :: Libraries :: Python Modules
Classifier: Topic :: System :: Hardware
